multiproc_tests/__init__.py
multiproc_tests/run.py
multiproc_tests-0.1.4.dist-info/LICENSE
multiproc_tests-0.1.4.dist-info/METADATA
multiproc_tests-0.1.4.dist-info/WHEEL
multiproc_tests-0.1.4.dist-info/top_level.txt
multiproc_tests-0.1.4.dist-info/RECORD
